{"total":540262,"data":[{"from_id":"54069298","from_name":"Muireled","to_id":"27934574","to_name":"SirhcEz","followed_at":"2019-06-12T20:51:11Z"},{"from_id":"441495892","from_name":"peterkys","to_id":"27934574","to_name":"SirhcEz","followed_at":"2019-06-12T19:41:35Z"},{"from_id":"441491288","from_name":"vxxxr","to_id":"27934574","to_name":"SirhcEz","followed_at":"2019-06-12T19:25:57Z"},{"from_id":"45034097","from_name":"HytLoL","to_id":"27934574","to_name":"SirhcEz","followed_at":"2019-06-12T19:01:23Z"},{"from_id":"441303490","from_name":"yacine6895","to_id":"27934574","to_name":"SirhcEz","followed_at":"2019-06-12T18:46:51Z"},{"from_id":"106711676","from_name":"theenigmasandwich","to_id":"27934574","to_name":"SirhcEz","followed_at":"2019-06-12T17:47:25Z"},{"from_id":"441472830","from_name":"some_kind_of_toilet","to_id":"27934574","to_name":"SirhcEz","followed_at":"2019-06-12T17:27:13Z"},{"from_id":"124365461","from_name":"shakemilki","to_id":"27934574","to_name":"SirhcEz","followed_at":"2019-06-12T17:10:38Z"},{"from_id":"196888786","from_name":"javvabba","to_id":"27934574","to_name":"SirhcEz","followed_at":"2019-06-12T16:16:56Z"},{"from_id":"126667323","from_name":"abuweazel","to_id":"27934574","to_name":"SirhcEz","followed_at":"2019-06-12T15:56:41Z"},{"from_id":"2427849","from_name":"Jabikuta","to_id":"27934574","to_name":"SirhcEz","followed_at":"2019-06-12T14:16:50Z"},{"from_id":"109111951","from_name":"Nodrocx","to_id":"27934574","to_name":"SirhcEz","followed_at":"2019-06-12T13:27:36Z"},{"from_id":"182005616","from_name":"bigolecoon","to_id":"27934574","to_name":"SirhcEz","followed_at":"2019-06-12T13:26:31Z"},{"from_id":"125835659","from_name":"PapaBigHead","to_id":"27934574","to_name":"SirhcEz","followed_at":"2019-06-12T12:51:08Z"},{"from_id":"270277068","from_name":"cicciozio","to_id":"27934574","to_name":"SirhcEz","followed_at":"2019-06-12T12:38:42Z"},{"from_id":"184309977","from_name":"Geresz01","to_id":"27934574","to_name":"SirhcEz","followed_at":"2019-06-12T12:02:30Z"},{"from_id":"246171614","from_name":"r3asonabl3","to_id":"27934574","to_name":"SirhcEz","followed_at":"2019-06-12T11:37:39Z"},{"from_id":"135503092","from_name":"SaltyCarry","to_id":"27934574","to_name":"SirhcEz","followed_at":"2019-06-12T11:16:28Z"},{"from_id":"150279875","from_name":"draka2132","to_id":"27934574","to_name":"SirhcEz","followed_at":"2019-06-12T11:00:12Z"},{"from_id":"441421171","from_name":"boostdjanna","to_id":"27934574","to_name":"SirhcEz","followed_at":"2019-06-12T10:53:35Z"}],"pagination":{"cursor":"eyJiIjpudWxsLCJhIjp7IkN1cnNvciI6IjE1NjAzMzY4MTU4NDI5MzY3ODMifX0"}}