{"total":784038,"data":[{"from_id":"180267307","from_name":"Major_Hellion","to_id":"7236692","to_name":"DansGaming","followed_at":"2019-06-12T20:53:03Z"},{"from_id":"183615298","from_name":"0rion52","to_id":"7236692","to_name":"DansGaming","followed_at":"2019-06-12T20:44:26Z"},{"from_id":"416945094","from_name":"Any_Anna_S","to_id":"7236692","to_name":"DansGaming","followed_at":"2019-06-12T20:21:26Z"},{"from_id":"198735245","from_name":"MKVteam","to_id":"7236692","to_name":"DansGaming","followed_at":"2019-06-12T20:19:14Z"},{"from_id":"79790003","from_name":"ChitusNG","to_id":"7236692","to_name":"DansGaming","followed_at":"2019-06-12T20:19:11Z"},{"from_id":"228332984","from_name":"kirilfrolov847","to_id":"7236692","to_name":"DansGaming","followed_at":"2019-06-12T20:19:09Z"},{"from_id":"218384889","from_name":"chitus7","to_id":"7236692","to_name":"DansGaming","followed_at":"2019-06-12T20:19:07Z"},{"from_id":"413359197","from_name":"HasbeyTV","to_id":"7236692","to_name":"DansGaming","followed_at":"2019-06-12T20:18:24Z"},{"from_id":"133364532","from_name":"ecot0ne","to_id":"7236692","to_name":"DansGaming","followed_at":"2019-06-12T20:10:16Z"},{"from_id":"123061819","from_name":"sui_sei","to_id":"7236692","to_name":"DansGaming","followed_at":"2019-06-12T20:09:56Z"},{"from_id":"151501535","from_name":"supremesmite","to_id":"7236692","to_name":"DansGaming","followed_at":"2019-06-12T20:04:51Z"},{"from_id":"236491907","from_name":"pepitomb_","to_id":"7236692","to_name":"DansGaming","followed_at":"2019-06-12T20:00:57Z"},{"from_id":"160294449","from_name":"Jekaterinaa","to_id":"7236692","to_name":"DansGaming","followed_at":"2019-06-12T19:55:30Z"},{"from_id":"82463624","from_name":"nuke_666","to_id":"7236692","to_name":"DansGaming","followed_at":"2019-06-12T19:51:27Z"},{"from_id":"437675256","from_name":"happix9000","to_id":"7236692","to_name":"DansGaming","followed_at":"2019-06-12T19:47:23Z"},{"from_id":"152304399","from_name":"TheExcellentPotato","to_id":"7236692","to_name":"DansGaming","followed_at":"2019-06-12T19:40:41Z"},{"from_id":"441496320","from_name":"fireball_5830","to_id":"7236692","to_name":"DansGaming","followed_at":"2019-06-12T19:35:58Z"},{"from_id":"413412418","from_name":"pistol_pete0","to_id":"7236692","to_name":"DansGaming","followed_at":"2019-06-12T19:34:08Z"},{"from_id":"441494697","from_name":"zmonadologizowana","to_id":"7236692","to_name":"DansGaming","followed_at":"2019-06-12T19:33:53Z"},{"from_id":"74136621","from_name":"yama_azumi","to_id":"7236692","to_name":"DansGaming","followed_at":"2019-06-12T19:21:29Z"}],"pagination":{"cursor":"eyJiIjpudWxsLCJhIjp7IkN1cnNvciI6IjE1NjAzNjcyODk1OTU3MjA4MjUifX0"}}