{"total":1022559,"data":[{"from_id":"58304138","from_name":"Antbone83","to_id":"21130533","to_name":"Nadeshot","followed_at":"2019-06-12T20:34:29Z"},{"from_id":"441493963","from_name":"Tuld","to_id":"21130533","to_name":"Nadeshot","followed_at":"2019-06-12T20:15:04Z"},{"from_id":"401033935","from_name":"extra_spoke","to_id":"21130533","to_name":"Nadeshot","followed_at":"2019-06-12T20:06:16Z"},{"from_id":"280703495","from_name":"slagleaustin","to_id":"21130533","to_name":"Nadeshot","followed_at":"2019-06-12T19:49:28Z"},{"from_id":"430400431","from_name":"reddkappa","to_id":"21130533","to_name":"Nadeshot","followed_at":"2019-06-12T19:47:55Z"},{"from_id":"441467587","from_name":"whispyyxo","to_id":"21130533","to_name":"Nadeshot","followed_at":"2019-06-12T19:39:23Z"},{"from_id":"64507799","from_name":"ceeebanks","to_id":"21130533","to_name":"Nadeshot","followed_at":"2019-06-12T19:39:08Z"},{"from_id":"206646792","from_name":"Laurenxg","to_id":"21130533","to_name":"Nadeshot","followed_at":"2019-06-12T19:30:07Z"},{"from_id":"207316006","from_name":"kmase14","to_id":"21130533","to_name":"Nadeshot","followed_at":"2019-06-12T19:29:58Z"},{"from_id":"174690061","from_name":"KhaoticOli","to_id":"21130533","to_name":"Nadeshot","followed_at":"2019-06-12T19:29:51Z"},{"from_id":"155241363","from_name":"kaednn","to_id":"21130533","to_name":"Nadeshot","followed_at":"2019-06-12T19:29:36Z"},{"from_id":"202990640","from_name":"bama_clan","to_id":"21130533","to_name":"Nadeshot","followed_at":"2019-06-12T19:24:37Z"},{"from_id":"274661152","from_name":"dragonbanisher_6","to_id":"21130533","to_name":"Nadeshot","followed_at":"2019-06-12T19:22:14Z"},{"from_id":"118065899","from_name":"tyler_flex","to_id":"21130533","to_name":"Nadeshot","followed_at":"2019-06-12T19:20:17Z"},{"from_id":"250441577","from_name":"stevenb3oo","to_id":"21130533","to_name":"Nadeshot","followed_at":"2019-06-12T19:18:50Z"},{"from_id":"106862722","from_name":"mattybobaaanga","to_id":"21130533","to_name":"Nadeshot","followed_at":"2019-06-12T19:17:18Z"},{"from_id":"140949071","from_name":"iPrayToCrom","to_id":"21130533","to_name":"Nadeshot","followed_at":"2019-06-12T19:13:29Z"},{"from_id":"70016825","from_name":"StormageddonStew","to_id":"21130533","to_name":"Nadeshot","followed_at":"2019-06-12T19:11:27Z"},{"from_id":"195084274","from_name":"cakismaximus","to_id":"21130533","to_name":"Nadeshot","followed_at":"2019-06-12T19:09:10Z"},{"from_id":"418990923","from_name":"the_friendlest_alien_","to_id":"21130533","to_name":"Nadeshot","followed_at":"2019-06-12T19:09:04Z"}],"pagination":{"cursor":"eyJiIjpudWxsLCJhIjp7IkN1cnNvciI6IjE1NjAzNjY1NDQ2OTg0ODk1NDEifX0"}}