{"total":1519602,"data":[{"from_id":"111030618","from_name":"ZeniJr","to_id":"22859264","to_name":"DreamHackCS","followed_at":"2019-06-12T19:53:35Z"},{"from_id":"152747434","from_name":"simobelhajjam","to_id":"22859264","to_name":"DreamHackCS","followed_at":"2019-06-12T19:51:47Z"},{"from_id":"441494958","from_name":"vf_death","to_id":"22859264","to_name":"DreamHackCS","followed_at":"2019-06-12T19:29:09Z"},{"from_id":"441493333","from_name":"jahakkk","to_id":"22859264","to_name":"DreamHackCS","followed_at":"2019-06-12T19:21:59Z"},{"from_id":"441492479","from_name":"3nkzik","to_id":"22859264","to_name":"DreamHackCS","followed_at":"2019-06-12T19:19:11Z"},{"from_id":"178641706","from_name":"Stovringdk","to_id":"22859264","to_name":"DreamHackCS","followed_at":"2019-06-12T19:17:57Z"},{"from_id":"431989478","from_name":"bizalhaoo","to_id":"22859264","to_name":"DreamHackCS","followed_at":"2019-06-12T19:00:07Z"},{"from_id":"62508224","from_name":"Bilboburrito","to_id":"22859264","to_name":"DreamHackCS","followed_at":"2019-06-12T18:59:44Z"},{"from_id":"172933409","from_name":"yoggi666i","to_id":"22859264","to_name":"DreamHackCS","followed_at":"2019-06-12T18:59:05Z"},{"from_id":"180201325","from_name":"weltman1","to_id":"22859264","to_name":"DreamHackCS","followed_at":"2019-06-12T18:45:50Z"},{"from_id":"105071364","from_name":"micha22017","to_id":"22859264","to_name":"DreamHackCS","followed_at":"2019-06-12T18:41:46Z"},{"from_id":"186466982","from_name":"tomusher32","to_id":"22859264","to_name":"DreamHackCS","followed_at":"2019-06-12T18:36:37Z"},{"from_id":"267722119","from_name":"itslokal","to_id":"22859264","to_name":"DreamHackCS","followed_at":"2019-06-12T18:36:16Z"},{"from_id":"166585410","from_name":"xXWeeeeXx","to_id":"22859264","to_name":"DreamHackCS","followed_at":"2019-06-12T18:35:16Z"},{"from_id":"120078265","from_name":"Stro_85","to_id":"22859264","to_name":"DreamHackCS","followed_at":"2019-06-12T18:30:35Z"},{"from_id":"91408537","from_name":"NeguiiN3","to_id":"22859264","to_name":"DreamHackCS","followed_at":"2019-06-12T18:24:06Z"},{"from_id":"270104034","from_name":"ryan_haywood","to_id":"22859264","to_name":"DreamHackCS","followed_at":"2019-06-12T18:23:25Z"},{"from_id":"186830187","from_name":"zylescsgo","to_id":"22859264","to_name":"DreamHackCS","followed_at":"2019-06-12T18:05:39Z"},{"from_id":"153532052","from_name":"o_duck21","to_id":"22859264","to_name":"DreamHackCS","followed_at":"2019-06-12T17:51:40Z"},{"from_id":"200901550","from_name":"deah2k_yt","to_id":"22859264","to_name":"DreamHackCS","followed_at":"2019-06-12T17:50:33Z"}],"pagination":{"cursor":"eyJiIjpudWxsLCJhIjp7IkN1cnNvciI6IjE1NjAzNjE4MzM5MzI3NDU5ODAifX0"}}