{"total":1760445,"data":[{"from_id":"439141349","from_name":"l_u_i_s__f_a_b_i_a_n__","to_id":"57793021","to_name":"LOLITOFDEZ","followed_at":"2019-06-12T20:43:16Z"},{"from_id":"441508030","from_name":"ds_domi_fierrudo","to_id":"57793021","to_name":"LOLITOFDEZ","followed_at":"2019-06-12T20:43:04Z"},{"from_id":"439357877","from_name":"geoxvlll","to_id":"57793021","to_name":"LOLITOFDEZ","followed_at":"2019-06-12T20:42:16Z"},{"from_id":"429673839","from_name":"cholomaster65","to_id":"57793021","to_name":"LOLITOFDEZ","followed_at":"2019-06-12T20:42:13Z"},{"from_id":"441353337","from_name":"xxhellscreamxx69","to_id":"57793021","to_name":"LOLITOFDEZ","followed_at":"2019-06-12T20:41:15Z"},{"from_id":"432164349","from_name":"alexvm60","to_id":"57793021","to_name":"LOLITOFDEZ","followed_at":"2019-06-12T20:40:57Z"},{"from_id":"441507539","from_name":"alan_10096","to_id":"57793021","to_name":"LOLITOFDEZ","followed_at":"2019-06-12T20:40:52Z"},{"from_id":"439549896","from_name":"juani116xd","to_id":"57793021","to_name":"LOLITOFDEZ","followed_at":"2019-06-12T20:40:33Z"},{"from_id":"259154064","from_name":"4p4w66p","to_id":"57793021","to_name":"LOLITOFDEZ","followed_at":"2019-06-12T20:40:29Z"},{"from_id":"441506756","from_name":"chars2719","to_id":"57793021","to_name":"LOLITOFDEZ","followed_at":"2019-06-12T20:40:22Z"},{"from_id":"223949907","from_name":"jaebe420","to_id":"57793021","to_name":"LOLITOFDEZ","followed_at":"2019-06-12T20:39:57Z"},{"from_id":"235683583","from_name":"matrixmatias","to_id":"57793021","to_name":"LOLITOFDEZ","followed_at":"2019-06-12T20:39:11Z"},{"from_id":"231333940","from_name":"gabiarg98","to_id":"57793021","to_name":"LOLITOFDEZ","followed_at":"2019-06-12T20:38:50Z"},{"from_id":"423531906","from_name":"panchobimbo","to_id":"57793021","to_name":"LOLITOFDEZ","followed_at":"2019-06-12T20:38:24Z"},{"from_id":"257530004","from_name":"pacolina","to_id":"57793021","to_name":"LOLITOFDEZ","followed_at":"2019-06-12T20:37:33Z"},{"from_id":"252092210","from_name":"ricardosp10","to_id":"57793021","to_name":"LOLITOFDEZ","followed_at":"2019-06-12T20:37:22Z"},{"from_id":"405462688","from_name":"thetebangames","to_id":"57793021","to_name":"LOLITOFDEZ","followed_at":"2019-06-12T20:37:13Z"},{"from_id":"415561254","from_name":"thelian13","to_id":"57793021","to_name":"LOLITOFDEZ","followed_at":"2019-06-12T20:36:24Z"},{"from_id":"441505993","from_name":"ulisesp23","to_id":"57793021","to_name":"LOLITOFDEZ","followed_at":"2019-06-12T20:35:13Z"},{"from_id":"441506082","from_name":"phony_max","to_id":"57793021","to_name":"LOLITOFDEZ","followed_at":"2019-06-12T20:34:57Z"}],"pagination":{"cursor":"eyJiIjpudWxsLCJhIjp7IkN1cnNvciI6IjE1NjAzNzE2OTc4MDk2NDc1ODcifX0"}}