{"total":526037,"data":[{"from_id":"229573564","from_name":"celsov1233","to_id":"36248926","to_name":"Kamikat","followed_at":"2019-06-12T20:20:08Z"},{"from_id":"407153525","from_name":"boibuloso1","to_id":"36248926","to_name":"Kamikat","followed_at":"2019-06-12T19:44:43Z"},{"from_id":"161938689","from_name":"Josezzin","to_id":"36248926","to_name":"Kamikat","followed_at":"2019-06-12T18:22:57Z"},{"from_id":"184962297","from_name":"OVERDOZANIMES","to_id":"36248926","to_name":"Kamikat","followed_at":"2019-06-12T18:21:40Z"},{"from_id":"269476593","from_name":"monoxinzhau","to_id":"36248926","to_name":"Kamikat","followed_at":"2019-06-12T18:00:47Z"},{"from_id":"191505391","from_name":"nowaybrat","to_id":"36248926","to_name":"Kamikat","followed_at":"2019-06-12T17:03:50Z"},{"from_id":"252749329","from_name":"lallybluew","to_id":"36248926","to_name":"Kamikat","followed_at":"2019-06-12T13:17:40Z"},{"from_id":"424285805","from_name":"isotmann","to_id":"36248926","to_name":"Kamikat","followed_at":"2019-06-12T08:20:33Z"},{"from_id":"178652888","from_name":"devilmaycare10","to_id":"36248926","to_name":"Kamikat","followed_at":"2019-06-12T02:41:01Z"},{"from_id":"238198537","from_name":"emmanuellaaa","to_id":"36248926","to_name":"Kamikat","followed_at":"2019-06-12T01:01:31Z"},{"from_id":"439827153","from_name":"7lanic","to_id":"36248926","to_name":"Kamikat","followed_at":"2019-06-11T23:44:59Z"},{"from_id":"177163011","from_name":"FlagTheLadino","to_id":"36248926","to_name":"Kamikat","followed_at":"2019-06-11T23:42:56Z"},{"from_id":"154466884","from_name":"arquira2000","to_id":"36248926","to_name":"Kamikat","followed_at":"2019-06-11T22:57:00Z"},{"from_id":"423491722","from_name":"drarcoLOL","to_id":"36248926","to_name":"Kamikat","followed_at":"2019-06-11T21:56:11Z"},{"from_id":"278027186","from_name":"elohimtds","to_id":"36248926","to_name":"Kamikat","followed_at":"2019-06-11T20:50:34Z"},{"from_id":"256491230","from_name":"MewAPerson","to_id":"36248926","to_name":"Kamikat","followed_at":"2019-06-11T20:04:53Z"},{"from_id":"137319264","from_name":"SailorClara","to_id":"36248926","to_name":"Kamikat","followed_at":"2019-06-11T18:27:39Z"},{"from_id":"253320765","from_name":"RafaTheKongg","to_id":"36248926","to_name":"Kamikat","followed_at":"2019-06-11T18:17:10Z"},{"from_id":"440212300","from_name":"m3cnobue","to_id":"36248926","to_name":"Kamikat","followed_at":"2019-06-11T18:08:05Z"},{"from_id":"68718844","from_name":"Funrise_","to_id":"36248926","to_name":"Kamikat","followed_at":"2019-06-11T16:22:22Z"}],"pagination":{"cursor":"eyJiIjpudWxsLCJhIjp7IkN1cnNvciI6IjE1NjAyNzAxNDIxOTU4MTc3ODEifX0"}}