{"total":1620591,"data":[{"from_id":"441511165","from_name":"melancholycutie","to_id":"54706574","to_name":"JoshOG","followed_at":"2019-06-12T21:01:25Z"},{"from_id":"440557732","from_name":"masseykev","to_id":"54706574","to_name":"JoshOG","followed_at":"2019-06-12T20:51:28Z"},{"from_id":"186816068","from_name":"jmun2002","to_id":"54706574","to_name":"JoshOG","followed_at":"2019-06-12T20:36:08Z"},{"from_id":"73929359","from_name":"RsM_jay","to_id":"54706574","to_name":"JoshOG","followed_at":"2019-06-12T20:27:03Z"},{"from_id":"102886474","from_name":"Marquez_Gaming","to_id":"54706574","to_name":"JoshOG","followed_at":"2019-06-12T20:25:41Z"},{"from_id":"196897492","from_name":"Mohredfield14","to_id":"54706574","to_name":"JoshOG","followed_at":"2019-06-12T20:22:53Z"},{"from_id":"162035327","from_name":"coribear124","to_id":"54706574","to_name":"JoshOG","followed_at":"2019-06-12T20:08:49Z"},{"from_id":"127389086","from_name":"LGmarques13","to_id":"54706574","to_name":"JoshOG","followed_at":"2019-06-12T20:04:14Z"},{"from_id":"216642785","from_name":"suf_288","to_id":"54706574","to_name":"JoshOG","followed_at":"2019-06-12T20:04:04Z"},{"from_id":"40385497","from_name":"mikkelwr","to_id":"54706574","to_name":"JoshOG","followed_at":"2019-06-12T20:03:54Z"},{"from_id":"89082667","from_name":"EmptyHolster","to_id":"54706574","to_name":"JoshOG","followed_at":"2019-06-12T20:02:00Z"},{"from_id":"225456430","from_name":"paperboat14","to_id":"54706574","to_name":"JoshOG","followed_at":"2019-06-12T19:52:52Z"},{"from_id":"148817278","from_name":"SebastianDSG","to_id":"54706574","to_name":"JoshOG","followed_at":"2019-06-12T19:50:56Z"},{"from_id":"189989083","from_name":"JoxziA","to_id":"54706574","to_name":"JoshOG","followed_at":"2019-06-12T19:49:03Z"},{"from_id":"87143586","from_name":"Hushe","to_id":"54706574","to_name":"JoshOG","followed_at":"2019-06-12T19:45:15Z"},{"from_id":"186660542","from_name":"Duper_Games","to_id":"54706574","to_name":"JoshOG","followed_at":"2019-06-12T19:44:41Z"},{"from_id":"99642453","from_name":"Picaso014","to_id":"54706574","to_name":"JoshOG","followed_at":"2019-06-12T19:40:22Z"},{"from_id":"220688341","from_name":"thebeanleader","to_id":"54706574","to_name":"JoshOG","followed_at":"2019-06-12T19:34:54Z"},{"from_id":"57746618","from_name":"Koroks","to_id":"54706574","to_name":"JoshOG","followed_at":"2019-06-12T19:34:05Z"},{"from_id":"107563361","from_name":"nin_Spark","to_id":"54706574","to_name":"JoshOG","followed_at":"2019-06-12T19:33:07Z"}],"pagination":{"cursor":"eyJiIjpudWxsLCJhIjp7IkN1cnNvciI6IjE1NjAzNjc5ODcyNzQwOTgxNzYifX0"}}