{"total":449945,"data":[{"from_id":"430676118","from_name":"sadiedunhill","to_id":"46864514","to_name":"Theokoles","followed_at":"2019-06-12T20:41:26Z"},{"from_id":"409780555","from_name":"valdymthebastarrd","to_id":"46864514","to_name":"Theokoles","followed_at":"2019-06-12T20:35:16Z"},{"from_id":"440561649","from_name":"Smokkls","to_id":"46864514","to_name":"Theokoles","followed_at":"2019-06-12T20:25:26Z"},{"from_id":"441504557","from_name":"yunusekici37","to_id":"46864514","to_name":"Theokoles","followed_at":"2019-06-12T20:23:08Z"},{"from_id":"253638587","from_name":"kaymayankoru00","to_id":"46864514","to_name":"Theokoles","followed_at":"2019-06-12T20:20:50Z"},{"from_id":"441445244","from_name":"qadosh3533","to_id":"46864514","to_name":"Theokoles","followed_at":"2019-06-12T20:14:04Z"},{"from_id":"179318359","from_name":"nilfcik","to_id":"46864514","to_name":"Theokoles","followed_at":"2019-06-12T20:11:05Z"},{"from_id":"278401947","from_name":"mnrVV","to_id":"46864514","to_name":"Theokoles","followed_at":"2019-06-12T20:10:34Z"},{"from_id":"228898076","from_name":"ulasbaba53","to_id":"46864514","to_name":"Theokoles","followed_at":"2019-06-12T20:01:36Z"},{"from_id":"441500429","from_name":"tortorus16","to_id":"46864514","to_name":"Theokoles","followed_at":"2019-06-12T20:00:57Z"},{"from_id":"420897119","from_name":"mobil_canavar","to_id":"46864514","to_name":"Theokoles","followed_at":"2019-06-12T19:56:58Z"},{"from_id":"441279485","from_name":"koylu_zed","to_id":"46864514","to_name":"Theokoles","followed_at":"2019-06-12T19:45:32Z"},{"from_id":"226486351","from_name":"hazzaroz","to_id":"46864514","to_name":"Theokoles","followed_at":"2019-06-12T19:41:06Z"},{"from_id":"438957384","from_name":"emirhangnlc","to_id":"46864514","to_name":"Theokoles","followed_at":"2019-06-12T19:40:30Z"},{"from_id":"49441703","from_name":"sinarikann","to_id":"46864514","to_name":"Theokoles","followed_at":"2019-06-12T19:40:21Z"},{"from_id":"441496109","from_name":"erenxia","to_id":"46864514","to_name":"Theokoles","followed_at":"2019-06-12T19:39:38Z"},{"from_id":"60946533","from_name":"BloodyDewil","to_id":"46864514","to_name":"Theokoles","followed_at":"2019-06-12T19:36:55Z"},{"from_id":"417999348","from_name":"lardozmd","to_id":"46864514","to_name":"Theokoles","followed_at":"2019-06-12T19:23:52Z"},{"from_id":"255184141","from_name":"sselim_1907","to_id":"46864514","to_name":"Theokoles","followed_at":"2019-06-12T19:21:35Z"},{"from_id":"277858381","from_name":"furkang716","to_id":"46864514","to_name":"Theokoles","followed_at":"2019-06-12T19:20:21Z"}],"pagination":{"cursor":"eyJiIjpudWxsLCJhIjp7IkN1cnNvciI6IjE1NjAzNjcyMjE1NTUzMjY5ODIifX0"}}